README.rst
setup.py
./agglo_tb/__init__.py
./agglo_tb/exceptions.py
./agglo_tb/_private/__init__.py
./agglo_tb/_private/conductor_proxy.py
./agglo_tb/_private/host_interface_proxy.py
./agglo_tb/_private/host_proxy.py
./agglo_tb/core/__init__.py
./agglo_tb/core/conductor.py
./agglo_tb/core/host.py
./agglo_tb/core/host_interface.py
./agglo_tb/core/io_connection_ethernet.py
./agglo_tb/core/node.py
./agglo_tb/core/target.py
./agglo_tb/core/test_bench.py
agglo_tb.egg-info/PKG-INFO
agglo_tb.egg-info/SOURCES.txt
agglo_tb.egg-info/dependency_links.txt
agglo_tb.egg-info/requires.txt
agglo_tb.egg-info/top_level.txt